powermate/__init__.py
powermate/__main__.py
powermate/base.py
powermate/linux.py
powermate/win.py
powermateusb-0.0.4.dist-info/LICENSE.txt
powermateusb-0.0.4.dist-info/METADATA
powermateusb-0.0.4.dist-info/WHEEL
powermateusb-0.0.4.dist-info/top_level.txt
powermateusb-0.0.4.dist-info/RECORD
