Metadata-Version: 2.1
Name: powermateusb
Version: 0.0.4
Summary: Cross-platform library for Griffin PowerMate
Home-page: https://github.com/sparkyb/powermate
Author: Ben Buchwald
Author-email: ben@ngcreative.com
License: MIT
Platform: UNKNOWN
Classifier: Development Status :: 3 - Alpha
Classifier: License :: OSI Approved :: MIT License
Classifier: Operating System :: Microsoft :: Windows
Classifier: Operating System :: POSIX :: Linux
Classifier: Programming Language :: Python :: 3.6
Classifier: Programming Language :: Python :: 3.7
Classifier: Programming Language :: Python :: 3.8
Classifier: Topic :: System :: Hardware :: Universal Serial Bus (USB) :: Human Interface Device (HID)
Requires-Python: >=3.6
License-File: LICENSE.txt
Requires-Dist: evdev (>=1.4.0) ; platform_system == "Linux"
Requires-Dist: pywinusb (~=0.4.2) ; platform_system == "Windows"
